fastutil/__init__.py
fastutil/data/__init__.py
fastutil/data/cleaner.py
fastutil/demo/__init__.py
fastutil/demo/env_init.py
fastutil/demo/model_to_pb.py
fastutil/model/__init__.py
fastutil/model/model_checkpoint.py
fastutil/model/model_util.py
fastutil/model/tf_util.py
fastutil/tool/__init__.py
fastutil/tool/common_util.py
fastutil/tool/custom_exception.py
fastutil/tool/file_util.py
fastutil/tool/fitlog_util.py
fastutil/tool/git_util.py
fastutil/tool/gpu_util.py
fastutil/tool/http_util.py
fastutil/tool/id_util.py
fastutil/tool/logging_util.py
fastutil/tool/loguru_util.py
fastutil/tool/message_util.py
fastutil/tool/signal_event.py
fastutil/tool/task_plan.py
fastutil/tool/task_util.py
fastutil/web/__init__.py
fastutil/web/fastapi_util.py
fastutil/web/flask_util.py
test/__init__.py
test/test_main.py
fastutil-1.1.2.dist-info/LICENSE
fastutil-1.1.2.dist-info/METADATA
fastutil-1.1.2.dist-info/WHEEL
fastutil-1.1.2.dist-info/entry_points.txt
fastutil-1.1.2.dist-info/top_level.txt
fastutil-1.1.2.dist-info/RECORD
