Metadata-Version: 2.1
Name: fastutil
Version: 1.1.2
Summary: common python util
Home-page: https://github.com/kylinat2688/fastutil
Author: kylin
Author-email: 464840061@qq.com
License: UNKNOWN
Platform: UNKNOWN
Requires-Python: >=3.4.0
Requires-Dist: pynvml
Requires-Dist: yagmail
Requires-Dist: loguru
Requires-Dist: setuptools
Requires-Dist: psutil
Requires-Dist: tqdm
Requires-Dist: zhconv
Requires-Dist: w3lib
Requires-Dist: zhon
Requires-Dist: fitlog
Requires-Dist: fastutil
Requires-Dist: flask
Requires-Dist: fastapi
Requires-Dist: starlette
Requires-Dist: requests
